{
  "generated_at": "2026-06-16",
  "generated_ts": "2026-06-16T10:16:33.043754",
  "macro_source": "IMF WEO Jan-2026 Update (WEO Apr-2026 sale el 14-Apr)",
  "market_source": "yfinance real-time",
  "countries": [
    {
      "code": "CN",
      "name": "China",
      "flag": "🇨🇳",
      "region": "Asia-Pacific",
      "gdp_growth": 4.5,
      "inflation": 0.5,
      "unemployment": 4.0,
      "current_account": 1.5,
      "rate_direction": "CUTTING",
      "policy_rate": 1.5,
      "macro_notes": "Tregua aranceles 90 días (145%→30%). PBoC estimulando. Deuda inmobiliaria sector privado es el riesgo real.",
      "debt_to_gdp": 83.0,
      "currency_sovereign": true,
      "etf": "FXI",
      "index": "000001.SS",
      "etf_data": {
        "current": 35.03,
        "ma200": 37.9,
        "ma50": 35.98,
        "pct_from_200": -7.6,
        "pct_from_52h": -14.6,
        "position_in_range": 9.2,
        "ytd_return": -11.4,
        "m1_return": -5.2,
        "ma200_slope": 1.22,
        "w52_high": 40.99,
        "w52_low": 34.42
      },
      "index_data": {
        "current": 4091.89,
        "ma200": 3988.12,
        "ma50": 4073.39,
        "pct_from_200": 2.6,
        "pct_from_52h": -3.6,
        "position_in_range": 82.9,
        "ytd_return": 1.7,
        "m1_return": -1.0,
        "ma200_slope": 10.72,
        "w52_high": 4242.57,
        "w52_low": 3359.9
      },
      "currency_ytd": 3.5,
      "macro_score": 79.0,
      "market_score": 97.0,
      "macro_breakdown": [
        "GDP +4.5% → 25/30",
        "Inflación 0.5% → 15/25",
        "Desempleo 4.0% → 17/20",
        "Tipos CUTTING → 15/15",
        "C/A +1.5% GDP → 8/10",
        "Deuda 83% GDP → -1/0"
      ],
      "market_breakdown": [
        "vs 200MA -7.6% → 35/35",
        "Rango 52s: 9% → 30/30",
        "YTD -11.4% → 17/20",
        "Tendencia 200MA +1.22% → 15/15"
      ],
      "signal": "STRONG_BUY",
      "color": "#10b981",
      "combined_score": 88.9,
      "contrarian": false,
      "wait_pullback": false
    },
    {
      "code": "IN",
      "name": "India",
      "flag": "🇮🇳",
      "region": "Asia-Pacific",
      "gdp_growth": 6.5,
      "inflation": 4.2,
      "unemployment": 8.0,
      "current_account": -1.2,
      "rate_direction": "CUTTING",
      "policy_rate": 6.0,
      "macro_notes": "Motor de crecimiento global. RBI iniciando ciclo bajista de tipos.",
      "debt_to_gdp": 82.0,
      "currency_sovereign": true,
      "etf": "INDA",
      "index": "^BSESN",
      "etf_data": {
        "current": 49.26,
        "ma200": 51.59,
        "ma50": 48.72,
        "pct_from_200": -4.5,
        "pct_from_52h": -11.8,
        "position_in_range": 36.8,
        "ytd_return": -9.7,
        "m1_return": 2.6,
        "ma200_slope": -2.31,
        "w52_high": 55.86,
        "w52_low": 45.42
      },
      "index_data": {
        "current": 76808.48,
        "ma200": 80798.15,
        "ma50": 75997.55,
        "pct_from_200": -4.9,
        "pct_from_52h": -10.4,
        "position_in_range": 35.2,
        "ytd_return": -9.8,
        "m1_return": 2.1,
        "ma200_slope": -0.35,
        "w52_high": 85762.01,
        "w52_low": 71947.55
      },
      "currency_ytd": -4.9,
      "macro_score": 63.0,
      "market_score": 71.0,
      "macro_breakdown": [
        "GDP +6.5% → 30/30",
        "Inflación 4.2% → 10/25",
        "Desempleo 8.0% → 5/20",
        "Tipos CUTTING → 15/15",
        "C/A -1.2% GDP → 4/10",
        "Deuda 82% GDP → -1/0"
      ],
      "market_breakdown": [
        "vs 200MA -4.5% → 35/35",
        "Rango 52s: 37% → 20/30",
        "YTD -9.7% → 14/20",
        "Tendencia 200MA -2.31% → 2/15"
      ],
      "signal": "BUY",
      "color": "#22d3ee",
      "combined_score": 67.4,
      "contrarian": false,
      "wait_pullback": false
    },
    {
      "code": "DE",
      "name": "Germany",
      "flag": "🇩🇪",
      "region": "Europe",
      "gdp_growth": 1.1,
      "inflation": 1.9,
      "unemployment": 3.4,
      "current_account": 4.3,
      "rate_direction": "CUTTING",
      "policy_rate": 2.25,
      "macro_notes": "Recuperación gradual. Nuevo gobierno con mayor gasto fiscal. ECB recortando.",
      "debt_to_gdp": 64.0,
      "currency_sovereign": false,
      "etf": "EWG",
      "index": "^GDAXI",
      "etf_data": {
        "current": 41.84,
        "ma200": 41.08,
        "ma50": 41.51,
        "pct_from_200": 1.8,
        "pct_from_52h": -4.2,
        "position_in_range": 71.0,
        "ytd_return": 0.3,
        "m1_return": 3.2,
        "ma200_slope": -0.32,
        "w52_high": 43.68,
        "w52_low": 37.33
      },
      "index_data": {
        "current": 25081.41,
        "ma200": 24186.92,
        "ma50": 24397.18,
        "pct_from_200": 3.7,
        "pct_from_52h": -1.3,
        "position_in_range": 89.1,
        "ytd_return": 2.2,
        "m1_return": 3.2,
        "ma200_slope": 0.25,
        "w52_high": 25420.66,
        "w52_low": 22300.75
      },
      "currency_ytd": -1.2,
      "macro_score": 74.0,
      "market_score": 49.0,
      "macro_breakdown": [
        "GDP +1.1% → 9/30",
        "Inflación 1.9% → 25/25",
        "Desempleo 3.4% → 17/20",
        "Tipos CUTTING → 15/15",
        "C/A +4.3% GDP → 10/10",
        "Deuda 64% GDP (sin moneda propia) → -2/0"
      ],
      "market_breakdown": [
        "vs 200MA +1.8% → 28/35",
        "Rango 52s: 71% → 8/30",
        "YTD +0.3% → 8/20",
        "Tendencia 200MA -0.32% → 5/15"
      ],
      "signal": "BUY",
      "color": "#22d3ee",
      "combined_score": 60.3,
      "contrarian": false,
      "wait_pullback": false
    },
    {
      "code": "FR",
      "name": "France",
      "flag": "🇫🇷",
      "region": "Europe",
      "gdp_growth": 1.0,
      "inflation": 1.5,
      "unemployment": 7.3,
      "current_account": -0.9,
      "rate_direction": "CUTTING",
      "policy_rate": 2.25,
      "macro_notes": "Crecimiento moderado. Deuda elevada sin soberanía monetaria. Consolidación fiscal en curso.",
      "debt_to_gdp": 112.0,
      "currency_sovereign": false,
      "etf": "EWQ",
      "index": "^FCHI",
      "etf_data": {
        "current": 45.75,
        "ma200": 43.72,
        "ma50": 44.49,
        "pct_from_200": 4.7,
        "pct_from_52h": -3.1,
        "position_in_range": 79.3,
        "ytd_return": 3.4,
        "m1_return": 6.1,
        "ma200_slope": 4.94,
        "w52_high": 47.22,
        "w52_low": 40.12
      },
      "index_data": {
        "current": 8450.73,
        "ma200": 8099.14,
        "ma50": 8165.5,
        "pct_from_200": 4.3,
        "pct_from_52h": -2.0,
        "position_in_range": 84.3,
        "ytd_return": 3.1,
        "m1_return": 5.8,
        "ma200_slope": 3.9,
        "w52_high": 8620.93,
        "w52_low": 7537.57
      },
      "currency_ytd": -1.2,
      "macro_score": 55.0,
      "market_score": 59.0,
      "macro_breakdown": [
        "GDP +1.0% → 9/30",
        "Inflación 1.5% → 25/25",
        "Desempleo 7.3% → 9/20",
        "Tipos CUTTING → 15/15",
        "C/A -0.9% GDP → 6/10",
        "Deuda 112% GDP (sin moneda propia) → -9/0"
      ],
      "market_breakdown": [
        "vs 200MA +4.7% → 28/35",
        "Rango 52s: 79% → 8/30",
        "YTD +3.4% → 8/20",
        "Tendencia 200MA +4.94% → 15/15"
      ],
      "signal": "NEUTRAL",
      "color": "#94a3b8",
      "combined_score": 57.2,
      "contrarian": false,
      "wait_pullback": false
    },
    {
      "code": "AU",
      "name": "Australia",
      "flag": "🇦🇺",
      "region": "Asia-Pacific",
      "gdp_growth": 1.7,
      "inflation": 2.8,
      "unemployment": 4.0,
      "current_account": -1.8,
      "rate_direction": "CUTTING",
      "policy_rate": 3.85,
      "macro_notes": "RBA inició recortes en Feb-2026. Muy expuesta a China vía commodities.",
      "debt_to_gdp": 50.0,
      "currency_sovereign": true,
      "etf": "EWA",
      "index": "^AXJO",
      "etf_data": {
        "current": 28.6,
        "ma200": 27.17,
        "ma50": 28.79,
        "pct_from_200": 5.3,
        "pct_from_52h": -4.2,
        "position_in_range": 78.0,
        "ytd_return": 9.6,
        "m1_return": 1.0,
        "ma200_slope": 5.01,
        "w52_high": 29.84,
        "w52_low": 24.19
      },
      "index_data": {
        "current": 8917.7,
        "ma200": 8783.35,
        "ma50": 8747.32,
        "pct_from_200": 1.5,
        "pct_from_52h": -3.1,
        "position_in_range": 66.3,
        "ytd_return": 2.2,
        "m1_return": 3.3,
        "ma200_slope": -1.06,
        "w52_high": 9198.6,
        "w52_low": 8365.9
      },
      "currency_ytd": 5.9,
      "macro_score": 70.0,
      "market_score": 46.0,
      "macro_breakdown": [
        "GDP +1.7% → 9/30",
        "Inflación 2.8% → 25/25",
        "Desempleo 4.0% → 17/20",
        "Tipos CUTTING → 15/15",
        "C/A -1.8% GDP → 4/10",
        "Deuda 50% GDP → 0/0"
      ],
      "market_breakdown": [
        "vs 200MA +5.3% → 18/35",
        "Rango 52s: 78% → 8/30",
        "YTD +9.6% → 5/20",
        "Tendencia 200MA +5.01% → 15/15"
      ],
      "signal": "NEUTRAL",
      "color": "#94a3b8",
      "combined_score": 56.8,
      "contrarian": false,
      "wait_pullback": false
    },
    {
      "code": "KR",
      "name": "South Korea",
      "flag": "🇰🇷",
      "region": "Asia-Pacific",
      "gdp_growth": 2.3,
      "inflation": 2.0,
      "unemployment": 2.8,
      "current_account": 3.4,
      "rate_direction": "CUTTING",
      "policy_rate": 2.75,
      "macro_notes": "Exportaciones semiconductores fuertes. BOK recortando. Impacto aranceles EE.UU. moderado.",
      "debt_to_gdp": 54.0,
      "currency_sovereign": true,
      "etf": "EWY",
      "index": "^KS11",
      "etf_data": {
        "current": 211.45,
        "ma200": 120.12,
        "ma50": 173.08,
        "pct_from_200": 76.0,
        "pct_from_52h": -2.4,
        "position_in_range": 96.5,
        "ytd_return": 106.9,
        "m1_return": 18.2,
        "ma200_slope": 68.75,
        "w52_high": 216.7,
        "w52_low": 65.17
      },
      "index_data": {
        "current": 8726.6,
        "ma200": 5031.22,
        "ma50": 7087.21,
        "pct_from_200": 73.4,
        "pct_from_52h": -0.9,
        "position_in_range": 98.7,
        "ytd_return": 102.5,
        "m1_return": 9.3,
        "ma200_slope": 57.16,
        "w52_high": 8801.49,
        "w52_low": 2946.66
      },
      "currency_ytd": -4.2,
      "macro_score": 85.0,
      "market_score": 28.0,
      "macro_breakdown": [
        "GDP +2.3% → 15/30",
        "Inflación 2.0% → 25/25",
        "Desempleo 2.8% → 20/20",
        "Tipos CUTTING → 15/15",
        "C/A +3.4% GDP → 10/10",
        "Deuda 54% GDP → 0/0"
      ],
      "market_breakdown": [
        "vs 200MA +76.0% → 8/35",
        "Rango 52s: 96% → 3/30",
        "YTD +106.9% → 2/20",
        "Tendencia 200MA +68.75% → 15/15"
      ],
      "signal": "NEUTRAL",
      "color": "#94a3b8",
      "combined_score": 53.7,
      "contrarian": false,
      "wait_pullback": true
    },
    {
      "code": "MX",
      "name": "Mexico",
      "flag": "🇲🇽",
      "region": "Americas",
      "gdp_growth": 1.3,
      "inflation": 4.0,
      "unemployment": 2.9,
      "current_account": -0.1,
      "rate_direction": "CUTTING",
      "policy_rate": 8.5,
      "macro_notes": "Nearshoring beneficia al sector industrial. Peso volátil. Dependencia económica de EE.UU. alta.",
      "debt_to_gdp": 50.0,
      "currency_sovereign": true,
      "etf": "EWW",
      "index": "^MXX",
      "etf_data": {
        "current": 77.76,
        "ma200": 70.93,
        "ma50": 76.88,
        "pct_from_200": 9.6,
        "pct_from_52h": -2.9,
        "position_in_range": 90.5,
        "ytd_return": 13.3,
        "m1_return": 2.2,
        "ma200_slope": 19.82,
        "w52_high": 80.05,
        "w52_low": 56.02
      },
      "index_data": {
        "current": 67954.55,
        "ma200": 65652.63,
        "ma50": 68623.01,
        "pct_from_200": 3.5,
        "pct_from_52h": -5.1,
        "position_in_range": 77.3,
        "ytd_return": 5.9,
        "m1_return": -0.0,
        "ma200_slope": 13.32,
        "w52_high": 71601.35,
        "w52_low": 55517.81
      },
      "currency_ytd": 4.6,
      "macro_score": 68.0,
      "market_score": 41.0,
      "macro_breakdown": [
        "GDP +1.3% → 9/30",
        "Inflación 4.0% → 18/25",
        "Desempleo 2.9% → 20/20",
        "Tipos CUTTING → 15/15",
        "C/A -0.1% GDP → 6/10",
        "Deuda 50% GDP → 0/0"
      ],
      "market_breakdown": [
        "vs 200MA +9.6% → 18/35",
        "Rango 52s: 90% → 3/30",
        "YTD +13.3% → 5/20",
        "Tendencia 200MA +19.82% → 15/15"
      ],
      "signal": "NEUTRAL",
      "color": "#94a3b8",
      "combined_score": 53.2,
      "contrarian": false,
      "wait_pullback": false
    },
    {
      "code": "CH",
      "name": "Switzerland",
      "flag": "🇨🇭",
      "region": "Europe",
      "gdp_growth": 1.5,
      "inflation": 0.9,
      "unemployment": 2.5,
      "current_account": 10.2,
      "rate_direction": "HOLDING",
      "policy_rate": 0.25,
      "macro_notes": "Franco fuerte, deuda baja, inflación mínima. Refugio defensivo por excelencia.",
      "debt_to_gdp": 40.0,
      "currency_sovereign": true,
      "etf": "EWL",
      "index": "^SSMI",
      "etf_data": {
        "current": 61.68,
        "ma200": 58.33,
        "ma50": 60.47,
        "pct_from_200": 5.7,
        "pct_from_52h": -3.5,
        "position_in_range": 81.7,
        "ytd_return": 4.0,
        "m1_return": 2.7,
        "ma200_slope": 9.66,
        "w52_high": 63.95,
        "w52_low": 51.52
      },
      "index_data": {
        "current": 13782.91,
        "ma200": 12935.24,
        "ma50": 13254.42,
        "pct_from_200": 6.6,
        "pct_from_52h": -1.7,
        "position_in_range": 89.8,
        "ytd_return": 4.0,
        "m1_return": 4.3,
        "ma200_slope": 7.96,
        "w52_high": 14014.3,
        "w52_low": 11755.32
      },
      "currency_ytd": -0.3,
      "macro_score": 64.0,
      "market_score": 44.0,
      "macro_breakdown": [
        "GDP +1.5% → 9/30",
        "Inflación 0.9% → 15/25",
        "Desempleo 2.5% → 20/20",
        "Tipos HOLDING → 10/15",
        "C/A +10.2% GDP → 10/10",
        "Deuda 40% GDP → 0/0"
      ],
      "market_breakdown": [
        "vs 200MA +5.7% → 18/35",
        "Rango 52s: 82% → 3/30",
        "YTD +4.0% → 8/20",
        "Tendencia 200MA +9.66% → 15/15"
      ],
      "signal": "NEUTRAL",
      "color": "#94a3b8",
      "combined_score": 53.0,
      "contrarian": false,
      "wait_pullback": false
    },
    {
      "code": "GB",
      "name": "United Kingdom",
      "flag": "🇬🇧",
      "region": "Europe",
      "gdp_growth": 1.3,
      "inflation": 2.5,
      "unemployment": 4.4,
      "current_account": -3.3,
      "rate_direction": "CUTTING",
      "policy_rate": 4.25,
      "macro_notes": "BOE recortando con cautela. Inflación de servicios aún elevada.",
      "debt_to_gdp": 100.0,
      "currency_sovereign": true,
      "etf": "EWU",
      "index": "^FTSE",
      "etf_data": {
        "current": 46.21,
        "ma200": 43.81,
        "ma50": 46.26,
        "pct_from_200": 5.5,
        "pct_from_52h": -3.7,
        "position_in_range": 82.8,
        "ytd_return": 5.4,
        "m1_return": 2.9,
        "ma200_slope": 10.38,
        "w52_high": 47.99,
        "w52_low": 37.62
      },
      "index_data": {
        "current": 10497.65,
        "ma200": 9997.93,
        "ma50": 10406.56,
        "pct_from_200": 5.0,
        "pct_from_52h": -3.8,
        "position_in_range": 81.2,
        "ytd_return": 5.5,
        "m1_return": 3.0,
        "ma200_slope": 8.91,
        "w52_high": 10910.6,
        "w52_low": 8718.8
      },
      "currency_ytd": -0.4,
      "macro_score": 67.0,
      "market_score": 41.0,
      "macro_breakdown": [
        "GDP +1.3% → 9/30",
        "Inflación 2.5% → 25/25",
        "Desempleo 4.4% → 17/20",
        "Tipos CUTTING → 15/15",
        "C/A -3.3% GDP → 2/10",
        "Deuda 100% GDP → -1/0"
      ],
      "market_breakdown": [
        "vs 200MA +5.5% → 18/35",
        "Rango 52s: 83% → 3/30",
        "YTD +5.4% → 5/20",
        "Tendencia 200MA +10.38% → 15/15"
      ],
      "signal": "NEUTRAL",
      "color": "#94a3b8",
      "combined_score": 52.7,
      "contrarian": false,
      "wait_pullback": false
    },
    {
      "code": "US",
      "name": "United States",
      "flag": "🇺🇸",
      "region": "Americas",
      "gdp_growth": 2.4,
      "inflation": 2.9,
      "unemployment": 4.4,
      "current_account": -3.3,
      "rate_direction": "HOLDING",
      "policy_rate": 4.375,
      "macro_notes": "Economía resiliente pero aranceles añaden presión. Fed en pausa hasta ver inflación.",
      "debt_to_gdp": 123.0,
      "currency_sovereign": true,
      "etf": "SPY",
      "index": "^GSPC",
      "etf_data": {
        "current": 741.75,
        "ma200": 684.07,
        "ma50": 722.8,
        "pct_from_200": 8.4,
        "pct_from_52h": -2.3,
        "position_in_range": 89.5,
        "ytd_return": 8.9,
        "m1_return": -0.9,
        "ma200_slope": 8.21,
        "w52_high": 759.57,
        "w52_low": 589.28
      },
      "index_data": {
        "current": 7431.46,
        "ma200": 6881.99,
        "ma50": 7247.79,
        "pct_from_200": 8.0,
        "pct_from_52h": -2.3,
        "position_in_range": 89.1,
        "ytd_return": 8.4,
        "m1_return": -0.9,
        "ma200_slope": 7.66,
        "w52_high": 7609.78,
        "w52_low": 5967.84
      },
      "currency_ytd": null,
      "macro_score": 66.0,
      "market_score": 41.0,
      "macro_breakdown": [
        "GDP +2.4% → 15/30",
        "Inflación 2.9% → 25/25",
        "Desempleo 4.4% → 17/20",
        "Tipos HOLDING → 10/15",
        "C/A -3.3% GDP → 2/10",
        "Deuda 123% GDP → -3/0"
      ],
      "market_breakdown": [
        "vs 200MA +8.4% → 18/35",
        "Rango 52s: 90% → 3/30",
        "YTD +8.9% → 5/20",
        "Tendencia 200MA +8.21% → 15/15"
      ],
      "signal": "NEUTRAL",
      "color": "#94a3b8",
      "combined_score": 52.2,
      "contrarian": false,
      "wait_pullback": false
    },
    {
      "code": "BR",
      "name": "Brazil",
      "flag": "🇧🇷",
      "region": "Americas",
      "gdp_growth": 1.9,
      "inflation": 4.0,
      "unemployment": 7.0,
      "current_account": -2.4,
      "rate_direction": "HIKING",
      "policy_rate": 13.25,
      "macro_notes": "Inflación persistente fuerza tipos altos. Deuda elevada con dependencia exterior. Real bajo presión.",
      "debt_to_gdp": 92.0,
      "currency_sovereign": false,
      "etf": "EWZ",
      "index": "^BVSP",
      "etf_data": {
        "current": 34.64,
        "ma200": 33.89,
        "ma50": 37.6,
        "pct_from_200": 2.2,
        "pct_from_52h": -16.2,
        "position_in_range": 58.0,
        "ytd_return": 8.6,
        "m1_return": -3.5,
        "ma200_slope": 27.21,
        "w52_high": 41.34,
        "w52_low": 25.38
      },
      "index_data": {
        "current": 171133.0,
        "ma200": 166846.7,
        "ma50": 183035.24,
        "pct_from_200": 2.6,
        "pct_from_52h": -13.9,
        "position_in_range": 58.6,
        "ytd_return": 6.6,
        "m1_return": -4.1,
        "ma200_slope": 23.83,
        "w52_high": 198657.0,
        "w52_low": 132129.0
      },
      "currency_ytd": 8.9,
      "macro_score": 39.0,
      "market_score": 62.0,
      "macro_breakdown": [
        "GDP +1.9% → 9/30",
        "Inflación 4.0% → 18/25",
        "Desempleo 7.0% → 9/20",
        "Tipos HIKING → 4/15",
        "C/A -2.4% GDP → 4/10",
        "Deuda 92% GDP (sin moneda propia) → -5/0"
      ],
      "market_breakdown": [
        "vs 200MA +2.2% → 28/35",
        "Rango 52s: 58% → 14/30",
        "YTD +8.6% → 5/20",
        "Tendencia 200MA +27.21% → 15/15"
      ],
      "signal": "NEUTRAL",
      "color": "#94a3b8",
      "combined_score": 51.7,
      "contrarian": false,
      "wait_pullback": false
    },
    {
      "code": "CA",
      "name": "Canada",
      "flag": "🇨🇦",
      "region": "Americas",
      "gdp_growth": 1.4,
      "inflation": 2.5,
      "unemployment": 6.3,
      "current_account": -1.2,
      "rate_direction": "CUTTING",
      "policy_rate": 2.75,
      "macro_notes": "BOC recortando agresivamente. Impacto aranceles EE.UU.",
      "debt_to_gdp": 107.0,
      "currency_sovereign": true,
      "etf": "EWC",
      "index": "^GSPTSE",
      "etf_data": {
        "current": 58.93,
        "ma200": 53.84,
        "ma50": 57.71,
        "pct_from_200": 9.5,
        "pct_from_52h": -0.4,
        "position_in_range": 98.3,
        "ytd_return": 9.3,
        "m1_return": 3.1,
        "ma200_slope": 15.41,
        "w52_high": 59.18,
        "w52_low": 44.49
      },
      "index_data": {
        "current": 34937.9,
        "ma200": 32080.74,
        "ma50": 34118.37,
        "pct_from_200": 8.9,
        "pct_from_52h": -0.8,
        "position_in_range": 96.8,
        "ytd_return": 9.6,
        "m1_return": 2.0,
        "ma200_slope": 15.35,
        "w52_high": 35217.1,
        "w52_low": 26497.6
      },
      "currency_ytd": -2.0,
      "macro_score": 61.0,
      "market_score": 41.0,
      "macro_breakdown": [
        "GDP +1.4% → 9/30",
        "Inflación 2.5% → 25/25",
        "Desempleo 6.3% → 9/20",
        "Tipos CUTTING → 15/15",
        "C/A -1.2% GDP → 4/10",
        "Deuda 107% GDP → -1/0"
      ],
      "market_breakdown": [
        "vs 200MA +9.5% → 18/35",
        "Rango 52s: 98% → 3/30",
        "YTD +9.3% → 5/20",
        "Tendencia 200MA +15.41% → 15/15"
      ],
      "signal": "NEUTRAL",
      "color": "#94a3b8",
      "combined_score": 50.0,
      "contrarian": false,
      "wait_pullback": false
    },
    {
      "code": "ES",
      "name": "Spain",
      "flag": "🇪🇸",
      "region": "Europe",
      "gdp_growth": 2.4,
      "inflation": 2.6,
      "unemployment": 11.5,
      "current_account": 2.8,
      "rate_direction": "CUTTING",
      "policy_rate": 2.25,
      "macro_notes": "Mejor crecimiento de la eurozona pero deuda 108% GDP sin soberanía monetaria. Turismo récord.",
      "debt_to_gdp": 108.0,
      "currency_sovereign": false,
      "etf": "EWP",
      "index": "^IBEX",
      "etf_data": {
        "current": 58.3,
        "ma200": 52.39,
        "ma50": 56.05,
        "pct_from_200": 11.3,
        "pct_from_52h": 0.0,
        "position_in_range": 100.0,
        "ytd_return": 8.3,
        "m1_return": 6.5,
        "ma200_slope": 13.95,
        "w52_high": 58.3,
        "w52_low": 41.2
      },
      "index_data": {
        "current": 19103.9,
        "ma200": 17009.65,
        "ma50": 18041.46,
        "pct_from_200": 12.3,
        "pct_from_52h": 0.0,
        "position_in_range": 100.0,
        "ytd_return": 9.2,
        "m1_return": 7.6,
        "ma200_slope": 13.39,
        "w52_high": 19103.9,
        "w52_low": 13744.9
      },
      "currency_ytd": -1.2,
      "macro_score": 55.0,
      "market_score": 41.0,
      "macro_breakdown": [
        "GDP +2.4% → 15/30",
        "Inflación 2.6% → 25/25",
        "Desempleo 11.5% → 1/20",
        "Tipos CUTTING → 15/15",
        "C/A +2.8% GDP → 8/10",
        "Deuda 108% GDP (sin moneda propia) → -9/0"
      ],
      "market_breakdown": [
        "vs 200MA +11.3% → 18/35",
        "Rango 52s: 100% → 3/30",
        "YTD +8.3% → 5/20",
        "Tendencia 200MA +13.95% → 15/15"
      ],
      "signal": "NEUTRAL",
      "color": "#94a3b8",
      "combined_score": 47.3,
      "contrarian": false,
      "wait_pullback": false
    },
    {
      "code": "JP",
      "name": "Japan",
      "flag": "🇯🇵",
      "region": "Asia-Pacific",
      "gdp_growth": 0.6,
      "inflation": 2.1,
      "unemployment": 2.5,
      "current_account": 3.8,
      "rate_direction": "HIKING",
      "policy_rate": 0.5,
      "macro_notes": "BOJ normalizando muy lentamente. Deuda 255% GDP pero monetizada por BOJ. Crecimiento débil.",
      "debt_to_gdp": 255.0,
      "currency_sovereign": true,
      "etf": "EWJ",
      "index": "^N225",
      "etf_data": {
        "current": 94.06,
        "ma200": 83.79,
        "ma50": 89.86,
        "pct_from_200": 12.3,
        "pct_from_52h": 0.0,
        "position_in_range": 100.0,
        "ytd_return": 16.3,
        "m1_return": 3.8,
        "ma200_slope": 12.11,
        "w52_high": 94.06,
        "w52_low": 68.73
      },
      "index_data": {
        "current": 69404.5,
        "ma200": 53029.69,
        "ma50": 61229.62,
        "pct_from_200": 30.9,
        "pct_from_52h": 0.0,
        "position_in_range": 100.0,
        "ytd_return": 33.9,
        "m1_return": 14.1,
        "ma200_slope": 28.61,
        "w52_high": 69404.5,
        "w52_low": 38311.33
      },
      "currency_ytd": -2.2,
      "macro_score": 58.0,
      "market_score": 38.0,
      "macro_breakdown": [
        "GDP +0.6% → 4/30",
        "Inflación 2.1% → 25/25",
        "Desempleo 2.5% → 20/20",
        "Tipos HIKING → 4/15",
        "C/A +3.8% GDP → 10/10",
        "Deuda 255% GDP → -5/0"
      ],
      "market_breakdown": [
        "vs 200MA +12.3% → 18/35",
        "Rango 52s: 100% → 3/30",
        "YTD +16.3% → 2/20",
        "Tendencia 200MA +12.11% → 15/15"
      ],
      "signal": "NEUTRAL",
      "color": "#94a3b8",
      "combined_score": 47.0,
      "contrarian": false,
      "wait_pullback": false
    },
    {
      "code": "IT",
      "name": "Italy",
      "flag": "🇮🇹",
      "region": "Europe",
      "gdp_growth": 0.7,
      "inflation": 1.7,
      "unemployment": 6.1,
      "current_account": 1.3,
      "rate_direction": "CUTTING",
      "policy_rate": 2.25,
      "macro_notes": "Deuda 138% GDP sin moneda propia = riesgo sistémico eurozona. Crecimiento anémico. ECB TPI da soporte.",
      "debt_to_gdp": 138.0,
      "currency_sovereign": false,
      "etf": "EWI",
      "index": "FTSEMIB.MI",
      "etf_data": {
        "current": 59.88,
        "ma200": 53.22,
        "ma50": 57.13,
        "pct_from_200": 12.5,
        "pct_from_52h": 0.0,
        "position_in_range": 100.0,
        "ytd_return": 10.7,
        "m1_return": 5.9,
        "ma200_slope": 8.77,
        "w52_high": 59.88,
        "w52_low": 44.78
      },
      "index_data": {
        "current": 52454.1,
        "ma200": 45225.87,
        "ma50": 48930.26,
        "pct_from_200": 16.0,
        "pct_from_52h": 0.0,
        "position_in_range": 100.0,
        "ytd_return": 15.6,
        "m1_return": 7.8,
        "ma200_slope": 7.75,
        "w52_high": 52454.1,
        "w52_low": 38841.0
      },
      "currency_ytd": -1.2,
      "macro_score": 48.0,
      "market_score": 41.0,
      "macro_breakdown": [
        "GDP +0.7% → 4/30",
        "Inflación 1.7% → 25/25",
        "Desempleo 6.1% → 9/20",
        "Tipos CUTTING → 15/15",
        "C/A +1.3% GDP → 8/10",
        "Deuda 138% GDP (sin moneda propia) → -13/0"
      ],
      "market_breakdown": [
        "vs 200MA +12.5% → 18/35",
        "Rango 52s: 100% → 3/30",
        "YTD +10.7% → 5/20",
        "Tendencia 200MA +8.77% → 15/15"
      ],
      "signal": "NEUTRAL",
      "color": "#94a3b8",
      "combined_score": 44.2,
      "contrarian": false,
      "wait_pullback": false
    }
  ],
  "summary": {
    "strong_buy": [
      "CN"
    ],
    "buy": [
      "IN",
      "DE"
    ],
    "neutral": [
      "FR",
      "AU",
      "KR",
      "MX",
      "CH",
      "GB",
      "US",
      "BR",
      "CA",
      "ES",
      "JP",
      "IT"
    ],
    "short": [],
    "strong_short": []
  }
}