{
  "date": "2026-05-27",
  "timestamp": "2026-05-27T09:20:42.359151",
  "narrative": "Se observa un patr\u00f3n de compra recurrente en varios tickers, destacando la actividad en el sector europeo. La presencia de m\u00faltiples insiders comprando en el mismo ticker en un corto per\u00edodo sugiere una confianza corporativa alta. Esto puede ser una se\u00f1al adicional para inversores value/GARP, indicando potencial para crecimiento a largo plazo. La diversificaci\u00f3n sectorial es notable, aunque se observa una concentraci\u00f3n en el sector energ\u00e9tico y financiero.",
  "total_tickers": 13,
  "total_us": 5,
  "total_eu": 8,
  "top_picks": [
    {
      "ticker": "VRSK",
      "market": "US",
      "purchase_count": 6,
      "unique_insiders": 1,
      "confidence_score": 130.0,
      "days_span": 1
    },
    {
      "ticker": "TYL",
      "market": "US",
      "purchase_count": 5,
      "unique_insiders": 2,
      "confidence_score": 120.0,
      "days_span": 4
    },
    {
      "ticker": "AAL.L",
      "market": "EU",
      "purchase_count": 38,
      "unique_insiders": 13,
      "confidence_score": 100.0,
      "days_span": 66
    },
    {
      "ticker": "BA.L",
      "market": "EU",
      "purchase_count": 41,
      "unique_insiders": 13,
      "confidence_score": 100.0,
      "days_span": 59
    },
    {
      "ticker": "BAS.DE",
      "market": "EU",
      "purchase_count": 5,
      "unique_insiders": 5,
      "confidence_score": 100.0,
      "days_span": 4
    }
  ]
}