{
  "date": "2026-07-23",
  "timestamp": "2026-07-23T07:41:47.376497",
  "narrative": "Se observa un patr\u00f3n de confianza alta en varios tickers europeos, con m\u00faltiples insiders comprando en el mismo per\u00edodo. Esto sugiere una visi\u00f3n optimista compartida entre los insiders sobre el desempe\u00f1o futuro de estas empresas. La concentraci\u00f3n de compras en un corto per\u00edodo de tiempo puede indicar una expectativa de aumento en el valor de las acciones. Para un inversor value/GARP, esta informaci\u00f3n puede ser una se\u00f1al adicional para considerar estas empresas en su an\u00e1lisis de inversi\u00f3n.",
  "total_tickers": 9,
  "total_us": 1,
  "total_eu": 8,
  "top_picks": [
    {
      "ticker": "AAL.L",
      "market": "EU",
      "purchase_count": 38,
      "unique_insiders": 12,
      "confidence_score": 100.0,
      "days_span": 69
    },
    {
      "ticker": "SGE.L",
      "market": "EU",
      "purchase_count": 9,
      "unique_insiders": 9,
      "confidence_score": 100.0,
      "days_span": 0
    },
    {
      "ticker": "MUV2.DE",
      "market": "EU",
      "purchase_count": 5,
      "unique_insiders": 5,
      "confidence_score": 100.0,
      "days_span": 6
    },
    {
      "ticker": "NG.L",
      "market": "EU",
      "purchase_count": 7,
      "unique_insiders": 3,
      "confidence_score": 100.0,
      "days_span": 61
    },
    {
      "ticker": "NWG.L",
      "market": "EU",
      "purchase_count": 17,
      "unique_insiders": 9,
      "confidence_score": 100.0,
      "days_span": 57
    }
  ]
}